PyMemoryEditor/__init__.py
PyMemoryEditor/__main__.py
PyMemoryEditor/enums.py
PyMemoryEditor/linux/functions.py
PyMemoryEditor/linux/process.py
PyMemoryEditor/linux/types.py
PyMemoryEditor/linux/ptrace/__init__.py
PyMemoryEditor/linux/ptrace/enums.py
PyMemoryEditor/linux/ptrace/ptrace.py
PyMemoryEditor/process/__init__.py
PyMemoryEditor/process/abstract.py
PyMemoryEditor/process/errors.py
PyMemoryEditor/process/info.py
PyMemoryEditor/process/util.py
PyMemoryEditor/sample/application.py
PyMemoryEditor/sample/main_application_window.py
PyMemoryEditor/sample/open_process_window.py
PyMemoryEditor/util/__init__.py
PyMemoryEditor/util/convert.py
PyMemoryEditor/util/scan.py
PyMemoryEditor/util/search/abstract.py
PyMemoryEditor/util/search/bmh.py
PyMemoryEditor/util/search/kmp.py
PyMemoryEditor/win32/functions.py
PyMemoryEditor/win32/process.py
PyMemoryEditor/win32/types.py
PyMemoryEditor/win32/enums/__init__.py
PyMemoryEditor/win32/enums/memory_allocation_states.py
PyMemoryEditor/win32/enums/memory_protections.py
PyMemoryEditor/win32/enums/memory_types.py
PyMemoryEditor/win32/enums/process_operations.py
PyMemoryEditor/win32/enums/standard_access_rights.py
pymemoryeditor-1.6.0.dist-info/METADATA
pymemoryeditor-1.6.0.dist-info/WHEEL
pymemoryeditor-1.6.0.dist-info/entry_points.txt
pymemoryeditor-1.6.0.dist-info/licenses/LICENSE
pymemoryeditor-1.6.0.dist-info/RECORD
