Metadata-Version: 2.4
Name: PyMemoryEditor
Version: 1.6.0
Summary: Multi-platform library developed with ctypes for reading, writing and searching at process memory, in a simple and friendly way with Python 3.
Project-URL: Homepage, https://github.com/JeanExtreme002/PyMemoryEditor
Author-email: Jean Loui Bernard Silva de Jesus <jeanextreme002@gmail.com>
License-Expression: MIT
License-File: LICENSE
Keywords: address,api,cheat,ctypes,debug,editor,linux,memory,override,pointer,process,ptrace,reader,readprocessmemory,scanner,track,virtual,win32,writeprocessmemory,writer
Classifier: Intended Audience :: Developers
Classifier: Intended Audience :: Information Technology
Classifier: Intended Audience :: Science/Research
Classifier: License :: OSI Approved :: MIT License
Classifier: Operating System :: Microsoft :: Windows
Classifier: Operating System :: POSIX :: Linux
Classifier: Programming Language :: Python :: 3 :: Only
Classifier: Programming Language :: Python :: 3.6
Classifier: Programming Language :: Python :: 3.7
Classifier: Programming Language :: Python :: 3.8
Classifier: Programming Language :: Python :: 3.9
Classifier: Programming Language :: Python :: 3.10
Classifier: Programming Language :: Python :: 3.11
Classifier: Programming Language :: Python :: 3.12
Classifier: Topic :: Scientific/Engineering
Classifier: Topic :: Security
Classifier: Topic :: System :: Monitoring
Requires-Python: >=3.6
Requires-Dist: psutil
Provides-Extra: tests
Requires-Dist: pytest; extra == 'tests'
